{
  "$schema": "https://typedoc.org/schema.json",
  "entryPoints": ["packages/react-web", "packages/react-native", "packages/client"],
  "entryPointStrategy": "packages",
  "name": "Lens SDK Reference",
  "out": "docs",
  "readme": "none",
  "plugin": ["typedoc-material-theme", "typedoc-plugin-extras"],
  "themeColor": "#c3e4cd",
  "customCss": "assets/docs.css",
  "navigation": {
    "includeCategories": false,
    "includeGroups": true,
    "includeFolders": false
  },
  "categorizeByGroup": true,
  "hideGenerator": true
}
